commind/__init__.py
commind/main.py
commind/core/__init__.py
commind/core/engine.py
commind/core/node.py
commind/core/nodecontent.py
commind/core/style.py
commind/core/tree.py
commind/help/__init__.py
commind/help/info.py
commind/ui/__init__.py
commind/ui/mainwindow.py
commind/v/__init__.py
commind/v/arrange.py
commind/v/render.py
commind-0.0.0.dist-info/LICENSE
commind-0.0.0.dist-info/METADATA
commind-0.0.0.dist-info/WHEEL
commind-0.0.0.dist-info/entry_points.txt
commind-0.0.0.dist-info/top_level.txt
commind-0.0.0.dist-info/RECORD
