Metadata-Version: 2.1
Name: commind
Version: 0.0.0
Summary: Generate mindmap with command line
Home-page: https://github.com/zwhsh/PyComMind
Author: zwhsh
License: GPL v3.0 License
Keywords: mindmap,mind,commandline
Platform: any
License-File: LICENSE
